erresire/CustomLensModel.py
erresire/__init__.py
erresire/create_lens_model.py
erresire/create_lens_pop.py
erresire/lens_model_extra_methods.py
erresire-0.1.4.dist-info/licenses/LICENSE
erresire-0.1.4.dist-info/METADATA
erresire-0.1.4.dist-info/WHEEL
erresire-0.1.4.dist-info/top_level.txt
erresire-0.1.4.dist-info/RECORD
