Metadata-Version: 2.4
Name: erresire
Version: 0.1.4
Summary: Simulate large populations of strong gravitational lenses (Monte Carlo‑based).
Author-email: Lorena Mezini <lormezini@gmail.com>
License: MIT
Project-URL: Repository, https://github.com/lmezini/Erresire
Project-URL: Homepage, https://github.com/lmezini/Erresire
Requires-Python: >=3.8
License-File: LICENSE
Requires-Dist: numpy
Requires-Dist: pandas
Requires-Dist: lenstronomy
Requires-Dist: shapely
Requires-Dist: colossus
Requires-Dist: scikit-learn
Requires-Dist: astropy
Dynamic: license-file
